fastapi_easylimiter/__init__.py
fastapi_easylimiter-0.2.5.dist-info/licenses/LICENSE
fastapi_easylimiter-0.2.5.dist-info/METADATA
fastapi_easylimiter-0.2.5.dist-info/WHEEL
fastapi_easylimiter-0.2.5.dist-info/top_level.txt
fastapi_easylimiter-0.2.5.dist-info/RECORD
