Metadata-Version: 2.4
Name: fastapi-easylimiter
Version: 0.2.5
Summary: High-performance async rate limiter for FastAPI with Redis or native in-memory backend
Author-email: cfunkz <cfunkz@duck.com>
License: MIT License
Project-URL: Homepage, https://github.com/cfunkz/fastapi-easylimiter
Project-URL: Documentation, https://github.com/cfunkz/fastapi-easylimiter
Project-URL: Source, https://github.com/cfunkz/fastapi-easylimiter
Project-URL: Issues, https://github.com/cfunkz/fastapi-easylimiter/issues
Requires-Python: >=3.9
License-File: LICENSE
Requires-Dist: fastapi>=0.110
Requires-Dist: starlette>=0.36
Requires-Dist: redis>=5.0.0
Dynamic: license-file
